rrb_package/__init__.py
rrb_package/my_module.py
rrb_package-0.1.1.dist-info/METADATA
rrb_package-0.1.1.dist-info/WHEEL
rrb_package-0.1.1.dist-info/top_level.txt
rrb_package-0.1.1.dist-info/RECORD
