Metadata-Version: 2.1
Name: rrb-package
Version: 0.1.1
Summary: My first pip installabe package
Home-page: https://github.com/rahulbhoyar1995/rrb_package
Author: Rahul Bhoyar
Author-email: rahulbhoyaroffice@gmail.com
License: UNKNOWN
Platform: UNKNOWN
Classifier: Programming Language :: Python :: 3
Classifier: License :: OSI Approved :: MIT License
Classifier: Operating System :: OS Independent
Requires-Python: >=3.6
